strgenp/__init__.py
strgenp/strgenp.py
strgenp-0.0.12.dist-info/METADATA
strgenp-0.0.12.dist-info/WHEEL
strgenp-0.0.12.dist-info/top_level.txt
strgenp-0.0.12.dist-info/RECORD
