Metadata-Version: 2.1
Name: strgenp
Version: 0.0.12
Summary: generate Random string
Home-page: UNKNOWN
Author: mahinbinhasan (Mahin Bin Hasan)
Author-email: <allmahin149@gmail.com>
License: UNKNOWN
Keywords: python,password generator
Platform: UNKNOWN
Classifier: Development Status :: 1 - Planning
Classifier: Intended Audience :: Developers
Classifier: Programming Language :: Python :: 3
Classifier: Operating System :: Unix
Classifier: Operating System :: MacOS :: MacOS X
Classifier: Operating System :: Microsoft :: Windows
